text2code/__init__.py
text2code-0.1.2.dist-info/AUTHORS
text2code-0.1.2.dist-info/LICENSE
text2code-0.1.2.dist-info/METADATA
text2code-0.1.2.dist-info/WHEEL
text2code-0.1.2.dist-info/pbr.json
text2code-0.1.2.dist-info/top_level.txt
text2code-0.1.2.dist-info/RECORD
