Metadata-Version: 2.1
Name: text2code
Version: 0.1.2
Summary: Parses arbitrary strings and returns a dictionary
Home-page: https://github.com/chrisnorman7/text2code
Author: Chris Norman
Author-email: chris.norman2@googlemail.com
License: MPL-2
Platform: UNKNOWN
